getuseragent/__init__.py
getuseragent/getuseragent.py
getuseragent/retrieve.py
getuseragent/user-agents/android.txt
getuseragent/user-agents/bots.txt
getuseragent/user-agents/chrome.txt
getuseragent/user-agents/edge.txt
getuseragent/user-agents/firefox.txt
getuseragent/user-agents/ie.txt
getuseragent/user-agents/ios.txt
getuseragent/user-agents/linux.txt
getuseragent/user-agents/mac.txt
getuseragent/user-agents/safari.txt
getuseragent/user-agents/windows.txt
getuseragent-0.0.6.dist-info/LICENSE
getuseragent-0.0.6.dist-info/METADATA
getuseragent-0.0.6.dist-info/WHEEL
getuseragent-0.0.6.dist-info/top_level.txt
getuseragent-0.0.6.dist-info/RECORD
