Metadata-Version: 2.1
Name: getuseragent
Version: 0.0.6
Summary: Get a random, popular, commonly-used user agent string. Random/fake/spoof user agents.
Home-page: https://github.com/pbiswell/getuseragent
Author: Paul Biswell
Author-email: pblabsdev@gmail.com
License: UNKNOWN
Keywords: getuseragent,get user agent,random user agent,fake user agent,fake useragent,random useragent,spoof useragent,spoof user agent,get useragent,useragent,user agent
Platform: UNKNOWN
Classifier: Development Status :: 5 - Production/Stable
Classifier: Environment :: Console
Classifier: Intended Audience :: Developers
Classifier: Intended Audience :: System Administrators
Classifier: Intended Audience :: Education
Classifier: Programming Language :: Python
Classifier: Programming Language :: Python :: 3
Classifier: Operating System :: MacOS :: MacOS X
Classifier: Operating System :: Microsoft :: Windows
Classifier: Operating System :: POSIX
Classifier: License :: OSI Approved :: Apache Software License
Classifier: Natural Language :: English
Classifier: Operating System :: OS Independent
Classifier: Topic :: Education :: Testing
Classifier: Topic :: Internet
Classifier: Topic :: Internet :: WWW/HTTP
License-File: LICENSE
